CHANGELOG.rst
MANIFEST.in
Makefile
Pipfile
README.rst
requirements.txt
setup.py
test-requirements.txt
tox.ini
db/routines.sql
db/schema.sql
src/vmshepherd_runtime_postgres_driver/__init__.py
src/vmshepherd_runtime_postgres_driver.egg-info/PKG-INFO
src/vmshepherd_runtime_postgres_driver.egg-info/SOURCES.txt
src/vmshepherd_runtime_postgres_driver.egg-info/dependency_links.txt
src/vmshepherd_runtime_postgres_driver.egg-info/entry_points.txt
src/vmshepherd_runtime_postgres_driver.egg-info/not-zip-safe
src/vmshepherd_runtime_postgres_driver.egg-info/requires.txt
src/vmshepherd_runtime_postgres_driver.egg-info/top_level.txt
tests/__init__.py
tests/unit/__init__.py
tests/unit/test__init__.py