Metadata-Version: 1.1
Name: vmshepherd-runtime-postgres-driver
Version: 1.2.1
Summary: Runtime and lock management based on Postgres for VmShepherd
Home-page: https://github.com/Dreamlab/vmshepherd-runtime-postgres-driver
Author: Dreamlab - PaaS KRK
Author-email: paas-support@dreamlab.pl
License: UNKNOWN
Keywords: vmshepherd,openstack,postgres,runtime,lock
Platform: UNKNOWN
Classifier: Programming Language :: Python :: 3.6
Classifier: Programming Language :: Python :: 3.7
Classifier: Operating System :: POSIX
